odoo/addons/account_journal_restrict_mode/README.rst
odoo/addons/account_journal_restrict_mode/__init__.py
odoo/addons/account_journal_restrict_mode/__manifest__.py
odoo/addons/account_journal_restrict_mode/hooks.py
odoo/addons/account_journal_restrict_mode/i18n/account_journal_restrict_mode.pot
odoo/addons/account_journal_restrict_mode/i18n/es.po
odoo/addons/account_journal_restrict_mode/i18n/it.po
odoo/addons/account_journal_restrict_mode/i18n/pt_BR.po
odoo/addons/account_journal_restrict_mode/models/__init__.py
odoo/addons/account_journal_restrict_mode/models/account_journal.py
odoo/addons/account_journal_restrict_mode/readme/CONTRIBUTORS.md
odoo/addons/account_journal_restrict_mode/readme/DESCRIPTION.md
odoo/addons/account_journal_restrict_mode/static/description/icon.png
odoo/addons/account_journal_restrict_mode/static/description/index.html
odoo/addons/account_journal_restrict_mode/tests/__init__.py
odoo/addons/account_journal_restrict_mode/tests/test_account_journal_restrict_mode.py
odoo_addon_account_journal_restrict_mode-19.0.1.0.0.4.dist-info/METADATA
odoo_addon_account_journal_restrict_mode-19.0.1.0.0.4.dist-info/WHEEL
odoo_addon_account_journal_restrict_mode-19.0.1.0.0.4.dist-info/top_level.txt
odoo_addon_account_journal_restrict_mode-19.0.1.0.0.4.dist-info/RECORD
